path_analysis/__init__.py
path_analysis/path_analysis.py
path_analysis-0.4.1.dist-info/LICENSE
path_analysis-0.4.1.dist-info/METADATA
path_analysis-0.4.1.dist-info/WHEEL
path_analysis-0.4.1.dist-info/top_level.txt
path_analysis-0.4.1.dist-info/RECORD
