Metadata-Version: 2.1
Name: path-analysis
Version: 0.4.1
Summary: Measurement Of Path Length For Photonic and Electrical systems
Home-page: UNKNOWN
Author: Mabrains LLC
Author-email: contact@mabrains.com
License: UNKNOWN
Platform: UNKNOWN
Classifier: Programming Language :: Python :: 3
Classifier: Intended Audience :: Developers
Classifier: Operating System :: POSIX :: Linux
Requires-Python: >3.9
License-File: LICENSE
Requires-Dist: PyYAML
Requires-Dist: Pyarrow
Requires-Dist: docopt
Requires-Dist: gdstk-mabrains
Requires-Dist: networkx
Requires-Dist: numpy
Requires-Dist: pandas
Requires-Dist: pyaml
Requires-Dist: quantiphy
Requires-Dist: tqdm
Requires-Dist: typing-extensions
